<annotation>
  <folder>resistor</folder>
  <filename>res304.jpeg</filename>
  <segmented>0</segmented>
  <size>
    <width>505</width>
    <height>351</height>
    <depth>3</depth>
  </size>
  <object>
    <name>resistor</name>
    <pose>Unspecified</pose>
    <truncated>0</truncated>
    <difficult>0</difficult>
    <bndbox>
      <xmin>209</xmin>
      <ymin>70</ymin>
      <xmax>252</xmax>
      <ymax>147</ymax>
    </bndbox>
  </object>
  <object>
    <name>resistor</name>
    <pose>Unspecified</pose>
    <truncated>0</truncated>
    <difficult>0</difficult>
    <bndbox>
      <xmin>79</xmin>
      <ymin>16</ymin>
      <xmax>150</xmax>
      <ymax>57</ymax>
    </bndbox>
  </object>
  <object>
    <name>resistor</name>
    <pose>Unspecified</pose>
    <truncated>0</truncated>
    <difficult>0</difficult>
    <bndbox>
      <xmin>290</xmin>
      <ymin>73</ymin>
      <xmax>330</xmax>
      <ymax>151</ymax>
    </bndbox>
  </object>
</annotation>
