<annotation>
  <folder>resistor</folder>
  <filename>res510.jpeg</filename>
  <segmented>0</segmented>
  <size>
    <width>256</width>
    <height>674</height>
    <depth>3</depth>
  </size>
  <object>
    <name>resistor</name>
    <pose>Unspecified</pose>
    <truncated>0</truncated>
    <difficult>0</difficult>
    <bndbox>
      <xmin>76</xmin>
      <ymin>29</ymin>
      <xmax>218</xmax>
      <ymax>96</ymax>
    </bndbox>
  </object>
  <object>
    <name>resistor</name>
    <pose>Unspecified</pose>
    <truncated>0</truncated>
    <difficult>0</difficult>
    <bndbox>
      <xmin>81</xmin>
      <ymin>206</ymin>
      <xmax>204</xmax>
      <ymax>268</ymax>
    </bndbox>
  </object>
  <object>
    <name>resistor</name>
    <pose>Unspecified</pose>
    <truncated>0</truncated>
    <difficult>0</difficult>
    <bndbox>
      <xmin>80</xmin>
      <ymin>394</ymin>
      <xmax>211</xmax>
      <ymax>459</ymax>
    </bndbox>
  </object>
</annotation>
