<annotation>
  <folder>resistor</folder>
  <filename>res641.jpeg</filename>
  <segmented>0</segmented>
  <size>
    <width>290</width>
    <height>324</height>
    <depth>3</depth>
  </size>
  <object>
    <name>resistor</name>
    <pose>Unspecified</pose>
    <truncated>0</truncated>
    <difficult>0</difficult>
    <bndbox>
      <xmin>137</xmin>
      <ymin>98</ymin>
      <xmax>196</xmax>
      <ymax>129</ymax>
    </bndbox>
  </object>
  <object>
    <name>resistor</name>
    <pose>Unspecified</pose>
    <truncated>0</truncated>
    <difficult>0</difficult>
    <bndbox>
      <xmin>210</xmin>
      <ymin>124</ymin>
      <xmax>242</xmax>
      <ymax>198</ymax>
    </bndbox>
  </object>
  <object>
    <name>resistor</name>
    <pose>Unspecified</pose>
    <truncated>0</truncated>
    <difficult>0</difficult>
    <bndbox>
      <xmin>106</xmin>
      <ymin>139</ymin>
      <xmax>146</xmax>
      <ymax>197</ymax>
    </bndbox>
  </object>
</annotation>
